Strandness/Strandness.py
Strandness/__init__.py
Strandness/__main__.py
Strandness/_version.py
Strandness-1.0.0.dist-info/LICENSE
Strandness-1.0.0.dist-info/METADATA
Strandness-1.0.0.dist-info/WHEEL
Strandness-1.0.0.dist-info/entry_points.txt
Strandness-1.0.0.dist-info/top_level.txt
Strandness-1.0.0.dist-info/RECORD
