Metadata-Version: 2.1
Name: Strandness
Version: 1.0.0
Summary: Analyze strandness of RNAs-seq data
Home-page: https://pypi.org/project/Strandness/
Author: Benxia Hu
Author-email: hubenxia@gmail.com
Classifier: Programming Language :: Python :: 3
Classifier: License :: OSI Approved :: MIT License
Classifier: Operating System :: OS Independent
Requires-Python: >=3.12
License-File: LICENSE
Requires-Dist: numpy
Requires-Dist: pandas
Requires-Dist: argparse
